CHANGES.rst
MANIFEST.in
README.rst
requirements.txt
setup.cfg
setup.py
test_ansi.py
doc/changes.rst
doc/conf.py
doc/index.rst
doc/requirements.txt
sphinxcontrib/__init__.py
sphinxcontrib/ansi.py
sphinxcontrib/black-on-white.css
sphinxcontrib_ansi.egg-info/PKG-INFO
sphinxcontrib_ansi.egg-info/SOURCES.txt
sphinxcontrib_ansi.egg-info/dependency_links.txt
sphinxcontrib_ansi.egg-info/namespace_packages.txt
sphinxcontrib_ansi.egg-info/not-zip-safe
sphinxcontrib_ansi.egg-info/requires.txt
sphinxcontrib_ansi.egg-info/top_level.txt