Metadata-Version: 1.1
Name: sphinxcontrib-ansi
Version: 0.6.dev20201023
Summary: Sphinx extension ansi
Home-page: https://github.com/sphinx-contrib/ansi
Author: Sebastian Wiesner
Author-email: lunaryorn@googlemail.com
License: BSD
Download-URL: http://pypi.python.org/pypi/sphinxcontrib-ansi
Platform: any
Classifier: Development Status :: 4 - Beta
Classifier: Environment :: Console
Classifier: Environment :: Web Environment
Classifier: Intended Audience :: Developers
Classifier: License :: OSI Approved :: BSD License
Classifier: Operating System :: OS Independent
Classifier: Programming Language :: Python
Classifier: Topic :: Documentation
Classifier: Topic :: Utilities
